setuptools_github/__init__.py
setuptools_github/_build.py
setuptools_github/cli.py
setuptools_github/scm.py
setuptools_github/script.py
setuptools_github/tools.py
setuptools_github-0.4.2.dist-info/LICENSE
setuptools_github-0.4.2.dist-info/METADATA
setuptools_github-0.4.2.dist-info/WHEEL
setuptools_github-0.4.2.dist-info/entry_points.txt
setuptools_github-0.4.2.dist-info/top_level.txt
setuptools_github-0.4.2.dist-info/RECORD
