Metadata-Version: 2.1
Name: setuptools-github
Version: 0.4.2
Summary: supports github releases
Home-page: https://github.com/cav71/setuptools-github
Classifier: Development Status :: 4 - Beta
Classifier: Environment :: Console
Classifier: Intended Audience :: Developers
Classifier: Programming Language :: Python
Classifier: Programming Language :: Python :: 3
Classifier: Programming Language :: Python :: 3.8
Classifier: Programming Language :: Python :: 3.9
Classifier: Programming Language :: Python :: 3.10
Classifier: Programming Language :: Python :: 3.11
Classifier: Operating System :: OS Independent
Classifier: License :: OSI Approved :: BSD License
License-File: LICENSE
Requires-Dist: setuptools
Requires-Dist: typing-extensions
Requires-Dist: jinja2
